{
	"Primery": {
		"Blokirovka_reklamy_v_Ukoz": "Blokirovka_reklamy_v_Ukoz\/",
		"Izobrazhenie_na_menyu": "Izobrazhenie_na_menyu\/",
		"Kontekstnye_kommentarii": "Kontekstnye_kommentarii\/",
		"Napominanie_o_registratcii": "Napominanie_o_registratcii\/",
		"Obyavlenie": "Obyavlenie\/",
		"Oformlenie_izobrazhenij": "Oformlenie_izobrazhenij\/",
		"Peredacha_klassa_po_kliku": "Peredacha_klassa_po_kliku\/",
		"Prygu4ij_object": "Prygu4ij_object\/",
		"Schetchik_vremeni": "Schetchik_vremeni\/",
		"Slajdery": {
			"Prostoj_slajder": "Slajdery\/Prostoj_slajder\/",
			"Slajder_dlya_shapki": "Slajdery\/Slajder_dlya_shapki\/",
			"Slajder_s_animaciej": "Slajdery\/Slajder_s_animaciej\/"
		},
		"Smena_dizajna": "Smena_dizajna\/",
		"Smena_teksta": "Smena_teksta\/",
		"Ustanovka_video": "Ustanovka_video\/",
		"Uvelichenie_izobrazheniya": "Uvelichenie_izobrazheniya\/",
		"Vrashchenie_bloka": "Vrashchenie_bloka\/",
		"Zapret_kopirovaniya": "Zapret_kopirovaniya\/",
		"Zvuk_po_kliku": "Zvuk_po_kliku\/"
	}
}